libzt/version.py
libzt/__init__.py
libzt/sockets.py
libzt/_libzt.cpython-35m-x86_64-linux-gnu.so
libzt/select.py
libzt/libzt.py
libzt/node.py
libzt-1.8.4.dist-info/LICENSE.txt
libzt-1.8.4.dist-info/RECORD
libzt-1.8.4.dist-info/top_level.txt
libzt-1.8.4.dist-info/WHEEL
libzt-1.8.4.dist-info/METADATA
libzt-1.8.4.dist-info/THIRDPARTY.txt
