Metadata-Version: 2.1
Name: libzt
Version: 1.8.4
Summary: ZeroTier
Home-page: https://github.com/zerotier/libzt
Author: ZeroTier, Inc.
Author-email: joseph@zerotier.com
License: BUSL 1.1
Download-URL: https://github.com/zerotier/libzt/releases
Keywords: zerotier p2p peer-to-peer sdwan sdn virtual network socket tcp udp zt encryption encrypted
Platform: UNKNOWN
Classifier: Topic :: Internet
Classifier: Topic :: System :: Networking
Classifier: Topic :: Security :: Cryptography
Classifier: Intended Audience :: Developers
Classifier: Intended Audience :: Information Technology
Classifier: Intended Audience :: System Administrators
Classifier: Intended Audience :: Telecommunications Industry
Classifier: Intended Audience :: End Users/Desktop
Classifier: License :: Free for non-commercial use
Classifier: Operating System :: MacOS
Classifier: Operating System :: POSIX :: BSD
Classifier: Operating System :: POSIX :: Linux
Classifier: Operating System :: Unix
Classifier: Programming Language :: C
Classifier: Programming Language :: C++
Classifier: Programming Language :: Python
